[
  {"name":"Greek salad","description":"Food provides essential nutrients for overall health and well-being","price":12,"category":"Salad","imageUrl":"http://localhost:5174/src/assets/assets/frontend_assets/food_1.png"},
  {"name":"Veg salad","description":"Food provides essential nutrients for overall health and well-being","price":18,"category":"Salad","imageUrl":"http://localhost:5174/src/assets/assets/frontend_assets/food_2.png"},
  {"name":"Clover Salad","description":"Food provides essential nutrients for overall health and well-being","price":16,"category":"Salad","imageUrl":"http://localhost:5174/src/assets/assets/frontend_assets/food_3.png"},
  {"name":"Chicken Salad","description":"Food provides essential nutrients for overall health and well-being","price":24,"category":"Salad","imageUrl":"http://localhost:5174/src/assets/assets/frontend_assets/food_4.png"},
  {"name":"Lasagna Rolls","description":"Food provides essential nutrients for overall health and well-being","price":14,"category":"Rolls","imageUrl":"http://localhost:5174/src/assets/assets/frontend_assets/food_5.png"},
  {"name":"Peri Peri Rolls","description":"Food provides essential nutrients for overall health and well-being","price":12,"category":"Rolls","imageUrl":"http://localhost:5174/src/assets/assets/frontend_assets/food_6.png"},
  {"name":"Chicken Rolls","description":"Food provides essential nutrients for overall health and well-being","price":20,"category":"Rolls","imageUrl":"http://localhost:5174/src/assets/assets/frontend_assets/food_7.png"},
  {"name":"Veg Rolls","description":"Food provides essential nutrients for overall health and well-being","price":15,"category":"Rolls","imageUrl":"http://localhost:5174/src/assets/assets/frontend_assets/food_8.png"},
  {"name":"Ripple Ice Cream","description":"Food provides essential nutrients for overall health and well-being","price":14,"category":"Deserts","imageUrl":"http://localhost:5174/src/assets/assets/frontend_assets/food_9.png"},
  {"name":"Fruit Ice Cream","description":"Food provides essential nutrients for overall health and well-being","price":22,"category":"Deserts","imageUrl":"http://localhost:5174/src/assets/assets/frontend_assets/food_10.png"},
  {"name":"Jar Ice Cream","description":"Food provides essential nutrients for overall health and well-being","price":10,"category":"Deserts","imageUrl":"http://localhost:5174/src/assets/assets/frontend_assets/food_11.png"},
  {"name":"Vanilla Ice Cream","description":"Food provides essential nutrients for overall health and well-being","price":12,"category":"Deserts","imageUrl":"http://localhost:5174/src/assets/assets/frontend_assets/food_12.png"},
  {"name":"Chicken Sandwich","description":"Food provides essential nutrients for overall health and well-being","price":12,"category":"Sandwich","imageUrl":"http://localhost:5174/src/assets/assets/frontend_assets/food_13.png"},
  {"name":"Vegan Sandwich","description":"Food provides essential nutrients for overall health and well-being","price":18,"category":"Sandwich","imageUrl":"http://localhost:5174/src/assets/assets/frontend_assets/food_14.png"},
  {"name":"Grilled Sandwich","description":"Food provides essential nutrients for overall health and well-being","price":16,"category":"Sandwich","imageUrl":"http://localhost:5174/src/assets/assets/frontend_assets/food_15.png"},
  {"name":"Bread Sandwich","description":"Food provides essential nutrients for overall health and well-being","price":24,"category":"Sandwich","imageUrl":"http://localhost:5174/src/assets/assets/frontend_assets/food_16.png"},
  {"name":"Cup Cake","description":"Food provides essential nutrients for overall health and well-being","price":14,"category":"Cake","imageUrl":"http://localhost:5174/src/assets/assets/frontend_assets/food_17.png"},
  {"name":"Vegan Cake","description":"Food provides essential nutrients for overall health and well-being","price":12,"category":"Cake","imageUrl":"http://localhost:5174/src/assets/assets/frontend_assets/food_18.png"},
  {"name":"Butterscotch Cake","description":"Food provides essential nutrients for overall health and well-being","price":20,"category":"Cake","imageUrl":"http://localhost:5174/src/assets/assets/frontend_assets/food_19.png"},
  {"name":"Sliced Cake","description":"Food provides essential nutrients for overall health and well-being","price":15,"category":"Cake","imageUrl":"http://localhost:5174/src/assets/assets/frontend_assets/food_20.png"},
  {"name":"Garlic Mushroom","description":"Food provides essential nutrients for overall health and well-being","price":14,"category":"Pure Veg","imageUrl":"http://localhost:5174/src/assets/assets/frontend_assets/food_21.png"},
  {"name":"Fried Cauliflower","description":"Food provides essential nutrients for overall health and well-being","price":22,"category":"Pure Veg","imageUrl":"http://localhost:5174/src/assets/assets/frontend_assets/food_22.png"},
  {"name":"Mix Veg Pulao","description":"Food provides essential nutrients for overall health and well-being","price":10,"category":"Pure Veg","imageUrl":"http://localhost:5174/src/assets/assets/frontend_assets/food_23.png"},
  {"name":"Rice Zucchini","description":"Food provides essential nutrients for overall health and well-being","price":12,"category":"Pure Veg","imageUrl":"http://localhost:5174/src/assets/assets/frontend_assets/food_24.png"},
  {"name":"Cheese Pasta","description":"Food provides essential nutrients for overall health and well-being","price":12,"category":"Pasta","imageUrl":"http://localhost:5174/src/assets/assets/frontend_assets/food_25.png"},
  {"name":"Tomato Pasta","description":"Food provides essential nutrients for overall health and well-being","price":18,"category":"Pasta","imageUrl":"http://localhost:5174/src/assets/assets/frontend_assets/food_26.png"},
  {"name":"Creamy Pasta","description":"Food provides essential nutrients for overall health and well-being","price":16,"category":"Pasta","imageUrl":"http://localhost:5174/src/assets/assets/frontend_assets/food_27.png"},
  {"name":"Chicken Pasta","description":"Food provides essential nutrients for overall health and well-being","price":24,"category":"Pasta","imageUrl":"http://localhost:5174/src/assets/assets/frontend_assets/food_28.png"},
  {"name":"Buttter Noodles","description":"Food provides essential nutrients for overall health and well-being","price":14,"category":"Noodles","imageUrl":"http://localhost:5174/src/assets/assets/frontend_assets/food_29.png"},
  {"name":"Veg Noodles","description":"Food provides essential nutrients for overall health and well-being","price":12,"category":"Noodles","imageUrl":"http://localhost:5174/src/assets/assets/frontend_assets/food_30.png"},
  {"name":"Somen Noodles","description":"Food provides essential nutrients for overall health and well-being","price":20,"category":"Noodles","imageUrl":"http://localhost:5174/src/assets/assets/frontend_assets/food_31.png"},
  {"name":"Cooked Noodles","description":"Food provides essential nutrients for overall health and well-being","price":15,"category":"Noodles","imageUrl":"http://localhost:5174/src/assets/assets/frontend_assets/food_32.png"}
]